{
  "simple": {
    "hi": [
      "10–12 मिनट श्वास-जागरूकता",
      "दिन का कठिन काम पहले",
      "सप्ताह में 60m नो-स्क्रीन",
      "प्रकृति-समय 20–30m"
    ]
  },
  "digital": {
    "hi": {
      "headline": "Sinaank Digital Remedies — आपकी ऊर्जा का सक्रियकरण",
      "bullets": [
        "Diamond Kundli (₹551) — Mobank/Yogank/Naamank का विश्लेषण",
        "Remedies ZIP — वॉलपेपर, टोन, एफ़र्मेशन",
        "Daily Digital Ritual — सुबह/दोपहर/शाम रूटीन"
      ],
      "cta": "यदि अधिक लाभ चाहते हैं तो Diamond Kundli डाउनलोड करें या Remedies ZIP सक्रिय करें।"
    }
  }
}